pyHES/HES.py
pyHES/__init__.py
pyHES-0.1.2.dist-info/LICENSE
pyHES-0.1.2.dist-info/METADATA
pyHES-0.1.2.dist-info/WHEEL
pyHES-0.1.2.dist-info/top_level.txt
pyHES-0.1.2.dist-info/RECORD
