Metadata-Version: 2.1
Name: pyHES
Version: 0.1.2
Summary: ⚕ (pyHES), Python ile Hayat Eve Sığar ile ilgili işlemleri yapan bir kütüphane.
Home-page: https://github.com/keyiflerolsun/pyHES
Author: keyiflerolsun
Author-email: keyiflerolsun@gmail.com
License: GPLv3+
Keywords: pyHES,KekikAkademi,keyiflerolsun
Platform: UNKNOWN
Classifier: Development Status :: 5 - Production/Stable
Classifier: License :: OSI Approved :: GNU General Public License v3 or later (GPLv3+)
Classifier: Programming Language :: Python :: 3
Requires-Python: >=3.9
License-File: LICENSE
Requires-Dist: requests
